MANIFEST.in
README.rst
setup.py
docs/HISTORY.rst
docs/INSTALL.rst
docs/LICENSE.GPL
docs/LICENSE.txt
quintagroup/__init__.py
quintagroup.theme.sunrain.egg-info/PKG-INFO
quintagroup.theme.sunrain.egg-info/SOURCES.txt
quintagroup.theme.sunrain.egg-info/dependency_links.txt
quintagroup.theme.sunrain.egg-info/entry_points.txt
quintagroup.theme.sunrain.egg-info/namespace_packages.txt
quintagroup.theme.sunrain.egg-info/not-zip-safe
quintagroup.theme.sunrain.egg-info/requires.txt
quintagroup.theme.sunrain.egg-info/top_level.txt
quintagroup/theme/__init__.py
quintagroup/theme/sunrain/README.txt
quintagroup/theme/sunrain/__init__.py
quintagroup/theme/sunrain/configure.zcml
quintagroup/theme/sunrain/test.py
quintagroup/theme/sunrain/profiles/default/metadata.xml
quintagroup/theme/sunrain/profiles/default/theme.xml
quintagroup/theme/sunrain/profiles/default/tinymce.xml
quintagroup/theme/sunrain/static/Gruntfile.js
quintagroup/theme/sunrain/static/index.html
quintagroup/theme/sunrain/static/manifest.cfg
quintagroup/theme/sunrain/static/package.json
quintagroup/theme/sunrain/static/rules.xml
quintagroup/theme/sunrain/static/css/rain.css
quintagroup/theme/sunrain/static/css/sun.css
quintagroup/theme/sunrain/static/css/sunrain-compiled.css
quintagroup/theme/sunrain/static/fonts/FontAwesome.otf
quintagroup/theme/sunrain/static/fonts/fontawesome-webfont.eot
quintagroup/theme/sunrain/static/fonts/fontawesome-webfont.svg
quintagroup/theme/sunrain/static/fonts/fontawesome-webfont.ttf
quintagroup/theme/sunrain/static/fonts/fontawesome-webfont.woff
quintagroup/theme/sunrain/static/fonts/fontawesome-webfont.woff2
quintagroup/theme/sunrain/static/fonts/search.eot
quintagroup/theme/sunrain/static/fonts/search.svg
quintagroup/theme/sunrain/static/fonts/search.ttf
quintagroup/theme/sunrain/static/fonts/search.woff
quintagroup/theme/sunrain/static/images/preview.png
quintagroup/theme/sunrain/static/images/rain_topbg.jpg
quintagroup/theme/sunrain/static/images/sun_topbg.jpg
quintagroup/theme/sunrain/static/js/mainnavigation.js
quintagroup/theme/sunrain/static/js/sunrain.js
quintagroup/theme/sunrain/static/less/sunrain.plone.less
quintagroup/theme/sunrain/static/less/sunrain.theme.less
quintagroup/theme/sunrain/static/less/variables.plone.less
quintagroup/theme/sunrain/static/less/font-awesome/animated.less
quintagroup/theme/sunrain/static/less/font-awesome/bordered-pulled.less
