Metadata-Version: 1.1
Name: quintagroup.theme.sunrain
Version: 7.2.5
Summary: Free Diazo Theme for Plone
Home-page: http://themes.quintagroup.com/product/sunrain
Author: Quintagroup
Author-email: skins@quintagroup.com
License: GPL
Keywords: web zope plone theme diazo quintagroup
Platform: UNKNOWN
Classifier: Framework :: Plone
Classifier: Intended Audience :: Developers
Classifier: Topic :: Software Development :: Libraries :: Python Modules
